{
  "name": "티거 I",
  "nameEn": "Tiger I (Panzerkampfwagen VI Tiger Ausf. E)",
  "image": "https://commons.wikimedia.org/wiki/Special:FilePath/Bundesarchiv_Bild_101I-299-1805-16%2C_Nordfrankreich%2C_Panzer_VI_%28Tiger_I%29.2.jpg?width=800",
  "category": "armor",
  "era": "worldwar",
  "origin": "나치 독일",
  "period": "1942년 ~ 1945년",
  "operators": ["독일 국방군", "무장 친위대"],
  "tags": ["전차", "중전차", "독일", "세계대전", "88mm"],
  "overview": [
    "티거 I(Tiger I)은 제2차 세계대전 당시 독일이 개발한 중전차로, 강력한 88mm 주포와 두꺼운 장갑으로 연합군에게 공포의 대상이었다.",
    "1대1 교전에서 거의 무적에 가까운 성능을 보였으나, 복잡한 구조와 높은 생산 비용, 낮은 신뢰성으로 총 1,347대만 생산되어 전세를 뒤집기에는 수량이 부족했다.",
    "미하엘 비트만 등 유명 전차 에이스들이 티거를 타고 활약하여 '전차의 왕'이라는 명성을 얻었다."
  ],
  "specs": [
    { "label": "전투 중량", "value": "약 57톤" },
    { "label": "주포", "value": "88mm KwK 36 L/56" },
    { "label": "최대 장갑", "value": "전면 100mm (수직)" },
    { "label": "엔진", "value": "마이바흐 HL 230 V12 가솔린 700마력" },
    { "label": "최대 속도", "value": "약 38km/h (도로)" },
    { "label": "항속 거리", "value": "약 195km (도로)" },
    { "label": "승무원", "value": "5명" },
    { "label": "생산량", "value": "1,347대" }
  ],
  "history": [
    "1930년대 후반부터 중전차 개발이 진행되었으나, 현실적 필요성은 1941년 동부전선에서 소련의 T-34와 KV-1에 직면한 후 급증했다.",
    "헨셸 사의 설계가 채택되어 1942년 8월 동부전선에 처음 투입되었다. 초기에는 기계적 문제가 빈발했으나, 점차 개선되었다.",
    "1942~1944년 약 1,347대 생산. 1944년부터 후속 모델인 티거 II(쾨니히스티거)가 등장했으나, 티거 I은 종전까지 계속 사용되었다."
  ],
  "design": [
    "티거 I의 핵심은 88mm KwK 36 주포이다. 원래 대공포인 Flak 18/36에서 파생된 이 포는 2,000m 거리에서 연합군 어떤 전차도 관통할 수 있었다.",
    "장갑은 두껍지만 경사 장갑이 아닌 수직 장갑이다. 이는 생산 편의를 위한 것이었으나, 실효 방어력에서는 경사 장갑 대비 불리했다.",
    "전폭이 철도 규격을 초과하여 수송 시 외부 궤도를 분리하고 좁은 궤도로 교체해야 했다. 이중 궤도 시스템은 정비를 복잡하게 만들었다.",
    "교차 배열된 전륜(Schachtellaufwerk) 현가장치는 주행 안정성이 뛰어났으나, 동부전선에서 진흙·얼음이 전륜 사이에 끼어 움직이지 못하는 경우가 발생했다."
  ],
  "operation": [
    "티거는 주로 독립 중전차 대대(schwere Panzer-Abteilung) 편제로 운용되어, 전선의 위기 지역에 투입되는 '소방대' 역할을 했다.",
    "최적의 교전 거리는 1,000m 이상으로, 원거리에서 적 전차를 일방적으로 타격하는 전술이 효과적이었다.",
    "연료 소비량이 극히 높아(도로 270L/100km) 보급이 큰 문제였으며, 고장 시 현장 수리가 어렵고 회수에 다른 티거가 필요하기도 했다."
  ],
  "combatRecord": [
    "레닌그라드 전선(1942): 최초 실전 투입. 습지 지형에서 기동 불능 상태에 빠지는 등 초기에 고전했다.",
    "쿠르스크 전투(1943): 대규모 기갑전에서 피격에 대한 높은 생존성을 입증. 그러나 기계적 고장으로 전투력 유지에 어려움.",
    "빌레르-보카주 전투(1944): 미하엘 비트만 SS 대위가 단 1대의 티거로 영국군 전차·차량 십여 대를 파괴한 전설적 교전.",
    "서부전선(1944~1945): 수적으로 압도하는 연합군 기갑 전력에 지속적으로 밀리면서도 방어전에서 높은 교환 비율을 유지."
  ],
  "variants": [
    { "name": "티거 I 초기형", "description": "캐폴라 없는 초기 생산형. 동부전선에서 최초 투입." },
    { "name": "티거 I 후기형", "description": "개량된 큐폴라, 궤도용 파스텐 코팅(치머릿) 적용. 1943년 중반 이후." },
    { "name": "슈투름티거", "description": "티거 차체에 380mm 로켓박격포를 탑재한 돌격포. 시가전용. 18대 생산." },
    { "name": "티거 II (쾨니히스티거)", "description": "후속 모델. 88mm L/71 장포신 + 경사 장갑. 더 강력하나 더 무겁고 비쌈." }
  ],
  "evaluation": [
    "티거 I은 개별 전투 성능에서 제2차 세계대전 최강의 전차 중 하나였다. 88mm 주포의 원거리 관통력과 두꺼운 장갑은 연합군에게 '티거 공포증(Tiger fear)'을 유발했다.",
    "그러나 전략적으로는 과잉 설계(over-engineering)의 대표적 사례이다. 1대의 티거 생산 비용으로 판터 1.5대, 4호 전차 2대 이상을 생산할 수 있었다.",
    "결국 티거가 보여준 교훈은 '최고의 무기'와 '전쟁에서 이기는 무기'는 다르다는 것이다. 소련의 T-34와 미국의 셔먼이 양으로 질을 이겼다."
  ],
  "related": [
    { "id": "armor/m4 sherman", "name": "M4 셔먼", "type": "경쟁 전차" },
    { "id": "armor/t-34", "name": "T-34", "type": "경쟁 전차" }
  ],
  "references": [
    "Thomas Jentz, 'Germany's Tiger Tanks: Tiger I and II', Schiffer Publishing, 2000",
    "Steven Zaloga, 'Tiger I Heavy Tank 1942-45', Osprey Publishing, 2005",
    "Patrick Agte, 'Michael Wittmann and the Waffen SS Tiger Commanders', Stackpole Books, 2006"
  ]
}
